anchorage/__init__.py
anchorage/anchor.py
anchorage/bookmarks.py
anchorage/cli.py
anchorage/anchor_infrs/__init__.py
anchorage/anchor_infrs/config.py
anchorage/anchor_infrs/infrastructure.py
anchorage/anchor_tools/__init__.py
anchorage/anchor_tools/local.py
anchorage/anchor_tools/online.py
anchorage/anchor_utils/__init__.py
anchorage/anchor_utils/aesthetic.py
anchorage/anchor_utils/file_conversion.py
anchorage/anchor_utils/regex.py
anchorage/anchor_utils/shell.py
anchorage/anchor_utils/system.py
tests/__init__.py
tests/test_bookmarks.py
tests/test_local.py
tests/test_online.py
anchorage-0.9.0.5.dist-info/LICENSE
anchorage-0.9.0.5.dist-info/METADATA
anchorage-0.9.0.5.dist-info/WHEEL
anchorage-0.9.0.5.dist-info/entry_points.txt
anchorage-0.9.0.5.dist-info/top_level.txt
anchorage-0.9.0.5.dist-info/RECORD
