Metadata-Version: 2.1
Name: anchorage
Version: 0.9.0.5
Summary: Anchor your little piece of internet.
Home-page: https://github.com/antonlopezr/anchorage
Author: Antonio Lopez Rivera
Author-email: antonlopezr99@gmail.com
License: UNKNOWN
Platform: UNKNOWN
Classifier: Programming Language :: Python :: 3
Classifier: License :: OSI Approved :: MIT License
Classifier: Operating System :: OS Independent
Requires-Python: >=3.7
Requires-Dist: numpy
Requires-Dist: rapidjson
Requires-Dist: toml
Requires-Dist: Python-Alexandria
Requires-Dist: archivenow
Requires-Dist: internetarchive
Requires-Dist: tqdm
Requires-Dist: pyfiglet
Requires-Dist: PyInquirer
Requires-Dist: prompt-toolkit (==1.0.14)
Requires-Dist: lz4
